gym_md/__init__.py
gym_md/envs/__init__.py
gym_md/envs/definition.py
gym_md/envs/grid.py
gym_md/envs/md_env.py
gym_md/envs/md_env_list.py
gym_md/envs/point.py
gym_md/envs/setting.py
gym_md/envs/singleton.py
gym_md/envs/agent/__init__.py
gym_md/envs/agent/actioner.py
gym_md/envs/agent/agent.py
gym_md/envs/agent/move_info.py
gym_md/envs/agent/pather.py
gym_md/envs/config/__init__.py
gym_md/envs/config/props_config.py
gym_md/envs/config/rewards_config.py
gym_md/envs/props/ConstantHolmgardLarge_0.json
gym_md/envs/props/ConstantHolmgardLarge_1.json
gym_md/envs/props/ConstantHolmgardLarge_10.json
gym_md/envs/props/ConstantHolmgardLarge_2.json
gym_md/envs/props/ConstantHolmgardLarge_3.json
gym_md/envs/props/ConstantHolmgardLarge_4.json
gym_md/envs/props/ConstantHolmgardLarge_5.json
gym_md/envs/props/ConstantHolmgardLarge_6.json
gym_md/envs/props/ConstantHolmgardLarge_7.json
gym_md/envs/props/ConstantHolmgardLarge_8.json
gym_md/envs/props/ConstantHolmgardLarge_9.json
gym_md/envs/props/ConstantHolmgard_0.json
gym_md/envs/props/ConstantHolmgard_1.json
gym_md/envs/props/ConstantHolmgard_10.json
gym_md/envs/props/ConstantHolmgard_2.json
gym_md/envs/props/ConstantHolmgard_3.json
gym_md/envs/props/ConstantHolmgard_4.json
gym_md/envs/props/ConstantHolmgard_5.json
gym_md/envs/props/ConstantHolmgard_6.json
gym_md/envs/props/ConstantHolmgard_7.json
gym_md/envs/props/ConstantHolmgard_8.json
gym_md/envs/props/ConstantHolmgard_9.json
gym_md/envs/props/Holmgard_0.json
gym_md/envs/props/Holmgard_1.json
gym_md/envs/props/Holmgard_10.json
gym_md/envs/props/Holmgard_2.json
gym_md/envs/props/Holmgard_3.json
gym_md/envs/props/Holmgard_4.json
gym_md/envs/props/Holmgard_5.json
gym_md/envs/props/Holmgard_6.json
gym_md/envs/props/Holmgard_7.json
gym_md/envs/props/Holmgard_8.json
gym_md/envs/props/Holmgard_9.json
gym_md/envs/props/check_1.json
gym_md/envs/props/check_2.json
gym_md/envs/props/check_3.json
gym_md/envs/props/edge.json
gym_md/envs/props/gene_1.json
gym_md/envs/props/gene_2.json
gym_md-0.5.2.dist-info/LICENSE
gym_md-0.5.2.dist-info/METADATA
gym_md-0.5.2.dist-info/WHEEL
gym_md-0.5.2.dist-info/top_level.txt
gym_md-0.5.2.dist-info/RECORD
